django_workflows_unistra-1.2.3.dist-info/DESCRIPTION.rst
django_workflows_unistra-1.2.3.dist-info/METADATA
django_workflows_unistra-1.2.3.dist-info/RECORD
django_workflows_unistra-1.2.3.dist-info/WHEEL
django_workflows_unistra-1.2.3.dist-info/metadata.json
django_workflows_unistra-1.2.3.dist-info/namespace_packages.txt
django_workflows_unistra-1.2.3.dist-info/top_level.txt
workflows/__init__.py
workflows/admin.py
workflows/mixins.py
workflows/models.py
workflows/tests.py
workflows/urls.py
workflows/utils.py
workflows/views.py
workflows/locale/de/LC_MESSAGES/django.mo
workflows/locale/de/LC_MESSAGES/django.po
workflows/migrations/0001_initial.py
workflows/migrations/__init__.py
