Metadata-Version: 2.0
Name: django-workflows-unistra
Version: 1.2.3
Summary: Generic workflow engine for Django.
Home-page: http://www.iqpp.de
Author: Kai Diefenbach
Author-email: kai.diefenbach@iqpp.de
License: BSD
Keywords: django workflows
Platform: UNKNOWN
Classifier: Development Status :: 5 - Production/Stable
Classifier: Environment :: Web Environment
Classifier: Framework :: Django
Classifier: License :: OSI Approved :: BSD License
Classifier: Operating System :: OS Independent
Classifier: Programming Language :: Python
Requires-Dist: setuptools
Requires-Dist: django-permissions-unistra
